spectralyze/models.py
spectralyze/opt.py
spectralyze/preprocessing.py
spectralyze-0.0.1.dist-info/LICENSE
spectralyze-0.0.1.dist-info/METADATA
spectralyze-0.0.1.dist-info/WHEEL
spectralyze-0.0.1.dist-info/top_level.txt
spectralyze-0.0.1.dist-info/RECORD
