Metadata-Version: 2.1
Name: spectralyze
Version: 0.0.1
Summary: spectral analysis
Author-email: Zefang Shen <zefang.zef.shen@gmail.com>
Maintainer-email: Zefang Shen <zefang.zef.shen@gmail.com>
License: BSD 3-Clause License
Project-URL: Homepage, https://www.github.com
Project-URL: Documentation, https://www.github.com
Project-URL: Repository, https://www.github.com
Keywords: spectra,spectroscopy
Requires-Python: >=3.8
License-File: LICENSE
Requires-Dist: numpy
Requires-Dist: pandas
Requires-Dist: scipy
